[
  {
    "documentID": "60:79423",
    "documentIdBarCode": "ER$KK#19DQ#1Q#20NX",
    "number": "0000000117",
    "status": "IssuedInvoice",
    "city": "град Шумен",
    "businessYear": 2026,
    "businessUnit": "0000",
    "costPosition": "",
    "warehouseCode": "0000",
    "documentCurrency": "EUR",
    "date": "2026-01-30",
    "documentLanguage": "Bulgarian",
    "paymentDueDate": "2026-02-06",
    "dateOfSupplyFrom": "2026-01-01",
    "dateOfSupplyUntil": "2026-01-31",
    "vatOutgoingDocumentVatClause": "NotRegistered",
    "vatTransactionType": "7",
    "vatReportingCurrency": "EUR",
    "domesticCurrency": "EUR",
    "recurringInvoice": "recurringCalendarMonth",
    "isRecurringInvoice": true,
    "buyerName": "ДЕНТАЛЕН ЦЕНТЪР ДЕНТ-ШУМЕН ЕООД",
    "buyerStreet": "Пл. Възраждане 1",
    "buyerPostalCode": "9700",
    "buyerCity": "град Шумен",
    "buyerCountry": "BG",
    "buyerTaxNumber": "000929108",
    "buyerVatRegistration": "None",
    "buyerCode": "000929108",
    "buyerDocumentID": "34:55155",
    "buyerEMail": "",
    "methodOfPayment": "BankTransfer",
    "bankAccountNumber": "BG60INTF40012076843552",
    "reference": "0000000117",
    "type": "Gross",
    "operatorName": "www.simpletax.bg Валери Петров",
    "issuedTimestamp": "2026-01-30 09:47:29",
    "superDiscountAmount": 0,
    "totalDiscount": 0,
    "documentAmount": 332.34,
    "amountAlreadyPaid": 0,
    "amountLeftToBePaid": 332.34,
    "totalAmountInDomCurr": 332.34,
    "totalAmountInVatReportingCurr": 332.34,
    "totalNetAmount": 332.34,
    "totalNetAmountInDomCurr": 332.34,
    "totalNetAmountInVatReportingCurr": 332.34,
    "totalVatBaseAmountNormalRate": 0,
    "totalVatBaseAmountLowerRate": 0,
    "totalVatBaseAmountZeroRate": 332.34,
    "totalVatBaseAmountInDomCurrNormalRate": 0,
    "totalVatBaseAmountInDomCurrLowerRate": 0,
    "totalVatBaseAmountInDomCurrZeroRate": 332.34,
    "totalVatBaseAmountInVatReportingCurrNormalRate": 0,
    "totalVatBaseAmountInVatReportingCurrLowerRate": 0,
    "totalVatBaseAmountInVatReportingCurrZeroRate": 332.34,
    "totalVatAmountNormalRate": 0,
    "totalVatAmountLowerRate": 0,
    "totalVatAmountInDomCurrNormalRate": 0,
    "totalVatAmountInDomCurrLowerRate": 0,
    "totalVatAmountInVatReportingCurrNormalRate": 0,
    "totalVatAmountInVatReportingCurrLowerRate": 0,
    "Items": [
      {
        "position": 1,
        "productCode": "000001",
        "productName": "Административно обслужване",
        "description": "",
        "productBarCode": "",
        "quantity": 1,
        "unit": "-",
        "currency": "BGN",
        "price": 650,
        "netPrice": 650,
        "priceInDocumentCurrency": 332.33972,
        "netPriceInDocumentCurrency": 332.33972,
        "discountPercentage": 0,
        "totalDiscountPercentage": 0,
        "discountAmount": 0,
        "vatPercentage": 0,
        "vatAmount": 0,
        "amount": 332.34,
        "amountWithoutDiscount": 332.34,
        "costPosition": ""
      }
    ]
  }
]