{
  "documentID": "60:85511",
  "documentIdBarCode": "ER$KK#19DQ#1Q#25X1",
  "number": "0000000129",
  "status": "IssuedInvoice",
  "city": "град Шумен",
  "businessYear": 2026,
  "businessUnit": "0000",
  "costPosition": "",
  "warehouseCode": "0000",
  "documentCurrency": "EUR",
  "date": "2026-04-01",
  "documentLanguage": "Bulgarian",
  "paymentDueDate": "2026-04-08",
  "dateOfSupplyFrom": "2026-03-01",
  "dateOfSupplyUntil": "2026-03-31",
  "vatOutgoingDocumentVatClause": "NotRegistered",
  "vatTransactionType": "7",
  "vatReportingCurrency": "EUR",
  "domesticCurrency": "EUR",
  "recurringInvoice": "recurringCalendarMonth",
  "isRecurringInvoice": true,
  "buyerName": "ДЕНТАЛЕН ЦЕНТЪР ДЕНТ-ШУМЕН ЕООД",
  "buyerStreet": "Пл. Възраждане 1",
  "buyerPostalCode": "9700",
  "buyerCity": "град Шумен",
  "buyerCountry": "BG",
  "buyerTaxNumber": "000929108",
  "buyerVatRegistration": "None",
  "buyerCode": "000929108",
  "buyerDocumentID": "34:55155",
  "buyerEMail": "000929108@evrofaktura.bg",
  "methodOfPayment": "BankTransfer",
  "bankAccountNumber": "BG60INTF40012076843552",
  "reference": "0000000129",
  "type": "Gross",
  "operatorName": "www.simpletax.bg Валери Петров",
  "issuedTimestamp": "2026-04-01 08:58:18",
  "superDiscountAmount": 0,
  "totalDiscount": 0,
  "documentAmount": 144,
  "amountAlreadyPaid": 0,
  "amountLeftToBePaid": 144,
  "totalAmountInDomCurr": 144,
  "totalAmountInVatReportingCurr": 144,
  "totalNetAmount": 144,
  "totalNetAmountInDomCurr": 144,
  "totalNetAmountInVatReportingCurr": 144,
  "totalVatBaseAmountNormalRate": 0,
  "totalVatBaseAmountLowerRate": 0,
  "totalVatBaseAmountZeroRate": 144,
  "totalVatBaseAmountInDomCurrNormalRate": 0,
  "totalVatBaseAmountInDomCurrLowerRate": 0,
  "totalVatBaseAmountInDomCurrZeroRate": 144,
  "totalVatBaseAmountInVatReportingCurrNormalRate": 0,
  "totalVatBaseAmountInVatReportingCurrLowerRate": 0,
  "totalVatBaseAmountInVatReportingCurrZeroRate": 144,
  "totalVatAmountNormalRate": 0,
  "totalVatAmountLowerRate": 0,
  "totalVatAmountInDomCurrNormalRate": 0,
  "totalVatAmountInDomCurrLowerRate": 0,
  "totalVatAmountInVatReportingCurrNormalRate": 0,
  "totalVatAmountInVatReportingCurrLowerRate": 0,
  "Items": [
    {
      "position": 1,
      "productCode": "000002",
      "productName": "Абонамент Софтуер",
      "description": "",
      "productBarCode": "",
      "quantity": 1,
      "unit": "-",
      "currency": "EUR",
      "price": 144,
      "netPrice": 144,
      "priceInDocumentCurrency": 144,
      "netPriceInDocumentCurrency": 144,
      "discountPercentage": 0,
      "totalDiscountPercentage": 0,
      "discountAmount": 0,
      "vatPercentage": 0,
      "vatAmount": 0,
      "amount": 144,
      "amountWithoutDiscount": 144,
      "costPosition": ""
    }
  ]
}